{
    "produtos": [
        {
            "id": "3714",
            "team": "celular",
            "image": 15.0,
            "price": 256,
            "onSale": "celular",
            "onSalePrice": 256,
            "kind": "celular",
            "continent": "celular"

        },
        {
            "id": "3714",
            "team": "celular",
            "image": 15.0,
            "price": 6546,
            "onSale": "celular",
            "onSalePrice": 256,
            "kind": "celular",
            "continent": "celular"

        },
        {
            "id": "3714",
            "team": "celular",
            "image": 15.0,
            "price": 6546,
            "onSale": "celular",
            "onSalePrice": 256,
            "kind": "celular",
            "continent": "celular"

        },
        {
            "id": "3714",
            "team": "celular",
            "image": 15.0,
            "price": 654,
            "onSale": "celular",
            "onSalePrice": 256,
            "kind": "celular",
            "continent": "celular"

        },
        {
            "id": "3714",
            "team": "celular",
            "image": 15.0,
            "price": 654,
            "onSale": "celular",
            "onSalePrice": 256,
            "kind": "celular",
            "continent": "celular"

        },
        {
            "id": "3714",
            "team": "celular",
            "image": 15.0,
            "price": 6546,
            "onSale": "celular",
            "onSalePrice": 256,
            "kind": "celular",
            "continent": "celular"

        }
    ]
}